flask_cassandra.py
Flask_Cassandra-0.13.dist-info/DESCRIPTION.rst
Flask_Cassandra-0.13.dist-info/METADATA
Flask_Cassandra-0.13.dist-info/RECORD
Flask_Cassandra-0.13.dist-info/metadata.json
Flask_Cassandra-0.13.dist-info/top_level.txt
Flask_Cassandra-0.13.dist-info/WHEEL
