Metadata-Version: 2.0
Name: Flask-Cassandra
Version: 0.13
Summary: Provides a connection to a Cassandra cluster in a Flask app
Home-page: http://terbiumlabs.com/flask-cassandra/
Author: Michael Moore
Author-email: michael@terbiumlabs.com
License: BSD
Platform: any
Classifier: Environment :: Web Environment
Classifier: Intended Audience :: Developers
Classifier: License :: OSI Approved :: BSD License
Classifier: Operating System :: OS Independent
Classifier: Programming Language :: Python
Classifier: Topic :: Internet :: WWW/HTTP :: Dynamic Content
Classifier: Topic :: Software Development :: Libraries :: Python Modules
Requires-Dist: Flask
Requires-Dist: cassandra-driver
